sip_docker_swarm/__init__.py
sip_docker_swarm/docker_swarm_client.py
sip_docker_swarm/version.py
skasip_docker_swarm-1.0.14.dist-info/LICENSE.md
skasip_docker_swarm-1.0.14.dist-info/METADATA
skasip_docker_swarm-1.0.14.dist-info/WHEEL
skasip_docker_swarm-1.0.14.dist-info/top_level.txt
skasip_docker_swarm-1.0.14.dist-info/RECORD
