Metadata-Version: 2.1
Name: skasip-docker-swarm
Version: 1.0.14
Summary: SIP Docker Swarm client library.
Home-page: https://github.com/SKA-ScienceDataProcessor/integration-prototype/tree/master/sip/execution_control/docker_swarm_api
Author: SKA SDP SIP team.
License: UNKNOWN
Platform: UNKNOWN
Classifier: Programming Language :: Python :: 3 :: Only
Classifier: Development Status :: 1 - Planning
Classifier: License :: OSI Approved :: BSD License
Requires-Dist: docker
